gimpformats/__init__.py
gimpformats/binaryiotools.py
gimpformats/GimpChannel.py
gimpformats/GimpGbrBrush.py
gimpformats/GimpGgrGradient.py
gimpformats/GimpGihBrushSet.py
gimpformats/GimpGpbBrush.py
gimpformats/GimpGplPalette.py
gimpformats/GimpGtpToolPreset.py
gimpformats/GimpImageHierarchy.py
gimpformats/GimpImageLevel.py
gimpformats/GimpIOBase.py
gimpformats/GimpLayer.py
gimpformats/GimpParasites.py
gimpformats/GimpPatPattern.py
gimpformats/GimpPrecision.py
gimpformats/GimpVbrBrush.py
gimpformats/GimpVectors.py
gimpformats/gimpXcfDocument.py
gimpformats/utils.py
gimpformats-2024.dist-info/LICENSE.txt
gimpformats-2024.dist-info/METADATA
gimpformats-2024.dist-info/WHEEL
gimpformats-2024.dist-info/RECORD
