Metadata-Version: 2.1
Name: gimpformats
Version: 2024
Summary: Pure python implementation of the gimp file format(s)
Home-page: https://github.com/FHPythonUtils/GimpFormats
License: LGPL-3.0-only
Author: FredHappyface
Requires-Python: >=3.9,<4.0
Classifier: Development Status :: 3 - Alpha
Classifier: Intended Audience :: Developers
Classifier: Intended Audience :: Education
Classifier: License :: OSI Approved :: GNU Lesser General Public License v3 (LGPLv3)
Classifier: Natural Language :: English
Classifier: Operating System :: OS Independent
Classifier: Programming Language :: Python :: 3
Classifier: Programming Language :: Python :: 3.9
Classifier: Programming Language :: Python :: 3.10
Classifier: Programming Language :: Python :: 3.11
Classifier: Programming Language :: Python :: 3.12
Classifier: Programming Language :: Python :: Implementation :: CPython
Classifier: Topic :: Multimedia :: Graphics
Classifier: Topic :: Software Development :: Libraries :: Python Modules
Classifier: Topic :: Utilities
Requires-Dist: Pillow (>=10.2.0,<11)
Requires-Dist: blendmodes (>=2024.1,<2026)
Requires-Dist: brackettree (>=0.2.5,<2)
Requires-Dist: numpy (>=1.26.4,<2)
Project-URL: Documentation, https://github.com/FHPythonUtils/GimpFormats/blob/master/README.md
Project-URL: Repository, https://github.com/FHPythonUtils/GimpFormats
